funguauniverse/__init__.py
funguauniverse/memoregressor.py
funguauniverse/servicetools/__init__.py
funguauniverse/servicetools/bgevent.py
funguauniverse/servicetools/event.py
funguauniverse/servicetools/hub.py
funguauniverse/servicetools/pipenode.py
funguauniverse/servicetools/processing.py
funguauniverse/servicetools/service.py
funguauniverse/servicetools/singleton.py
funguauniverse/servicetools/store_item.py
funguauniverse/spec/__init__.py
funguauniverse/spec/clients/__init__.py
funguauniverse/spec/clients/influx.py
funguauniverse/spec/clients/memory.py
funguauniverse/spec/clients/portfolio.py
funguauniverse/spec/clients/preprocessing.py
funguauniverse/spec/clients/price.py
funguauniverse/spec/clients/regressor.py
funguauniverse/utils/__init__.py
funguauniverse/utils/pipeline/__init__.py
funguauniverse/utils/pipeline/bgevent.py
funguauniverse/utils/pipeline/event.py
funguauniverse/utils/pipeline/hub.py
funguauniverse/utils/pipeline/memory.py
funguauniverse/utils/pipeline/pipenode.py
funguauniverse/utils/pipeline/processing.py
funguauniverse/utils/pipeline/service.py
funguauniverse/utils/pipeline/singleton.py
funguauniverse/utils/pipeline/store_item.py
funguauniverse/utils/pipeline/supernode.py
funguauniverse/utils/web/__init__.py
funguauniverse/utils/web/background_service.py
funguauniverse/utils/web/gunicorn_server.py
funguauniverse/utils/web/serviceclient.py
funguauniverse/utils/web/threadpoolmixin.py
funguauniverse/webservices/__init__.py
funguauniverse/webservices/gunicorn_server.py
funguauniverse-0.4.9.dist-info/METADATA
funguauniverse-0.4.9.dist-info/WHEEL
funguauniverse-0.4.9.dist-info/top_level.txt
funguauniverse-0.4.9.dist-info/RECORD
