Metadata-Version: 2.1
Name: funguauniverse
Version: 0.4.9
Summary: A set of class tools to run the Funguana Pipeline. Many irrelelavent parts
Home-page: UNKNOWN
Author: Kevin Hill
Author-email: kah.kevin.hill@gmail.com
License: UNKNOWN
Platform: UNKNOWN
Classifier: Programming Language :: Python :: 3
Classifier: License :: OSI Approved :: MIT License
Classifier: Operating System :: OS Independent
Requires-Dist: pytest
Requires-Dist: scipy
Requires-Dist: numpy
Requires-Dist: pandas
Requires-Dist: dask[complete]
Requires-Dist: ta-lib
Requires-Dist: loguru
Requires-Dist: spaceman
Requires-Dist: prometheus-client
Requires-Dist: requests-futures
Requires-Dist: influxdb
